{
  "manual": false,
  "urls": {
    "1923595242": {
      "success": {
        "timestamp": "2026-02-24T04:53:25.996336248Z"
      },
      "error": {
        "timestamp": "2026-02-23T04:54:05.725377869Z",
        "code": 502
      }
    },
    "-994408140": {
      "success": {
        "timestamp": "2026-02-05T04:58:55.205305755Z"
      }
    },
    "183369387": {
      "success": {
        "timestamp": "2026-02-24T04:53:25.839786Z"
      },
      "error": {
        "timestamp": "2026-02-23T04:54:05.618027196Z",
        "code": 502
      }
    },
    "-1306362930": {
      "success": {
        "timestamp": "2026-07-22T07:34:21.384375359Z"
      }
    },
    "1064437712": {
      "success": {
        "timestamp": "2026-07-22T07:34:21.899024430Z"
      }
    },
    "-523910190": {
      "error": {
        "timestamp": "2026-07-22T07:34:23.030135069Z",
        "code": 200
      }
    },
    "2020695478": {
      "error": {
        "timestamp": "2026-07-22T07:34:23.520776354Z",
        "code": 200
      }
    },
    "-553749233": {
      "success": {
        "timestamp": "2026-07-22T07:34:24.262862172Z"
      }
    }
  }
}