{
  "manual" : false,
  "urls" : {
    "132176070" : {
      "error" : {
        "timestamp" : "2025-12-01T04:25:14.334683181Z",
        "code" : 200
      }
    },
    "-1147687608" : {
      "error" : {
        "timestamp" : "2025-12-01T04:25:15.610737302Z",
        "code" : 200
      }
    },
    "-833734369" : {
      "error" : {
        "timestamp" : "2025-12-01T04:25:16.887484722Z",
        "code" : 200
      }
    },
    "-1520346210" : {
      "error" : {
        "timestamp" : "2025-12-01T04:25:17.275559025Z",
        "code" : 200
      }
    }
  }
}