{
  "manual": false,
  "urls": {
    "797659770": {
      "success": {
        "timestamp": "2023-07-07T03:46:05.688191Z"
      }
    },
    "293822310": {
      "success": {
        "timestamp": "2023-07-07T03:46:06.480726Z"
      }
    },
    "132176070": {
      "error": {
        "timestamp": "2026-03-14T05:01:14.288228789Z",
        "code": 200
      }
    },
    "-1147687608": {
      "error": {
        "timestamp": "2026-03-14T05:01:16.199746355Z",
        "code": 200
      }
    },
    "-833734369": {
      "error": {
        "timestamp": "2026-03-14T05:01:18.105732195Z",
        "code": 200
      }
    },
    "-1520346210": {
      "error": {
        "timestamp": "2026-03-14T05:01:18.874053877Z",
        "code": 200
      }
    }
  }
}