{
  "manual" : false,
  "urls" : {
    "459133350" : {
      "success" : {
        "timestamp" : "2025-12-14T03:41:21.385637403Z"
      },
      "error" : {
        "timestamp" : "2025-12-30T05:46:36.514319460Z",
        "code" : -1
      }
    },
    "1025221338" : {
      "success" : {
        "timestamp" : "2025-12-05T03:39:21.796748399Z"
      },
      "error" : {
        "timestamp" : "2025-12-30T05:46:30.708524708Z",
        "code" : -1
      }
    },
    "-1845738998" : {
      "success" : {
        "timestamp" : "2025-12-22T03:49:21.169269929Z"
      }
    },
    "1686323518" : {
      "success" : {
        "timestamp" : "2025-12-22T03:49:21.403507865Z"
      }
    }
  }
}