{
  "manual" : false,
  "urls" : {
    "1916447922" : {
      "success" : {
        "timestamp" : "2025-12-18T03:33:49.085824893Z"
      },
      "error" : {
        "timestamp" : "2025-12-30T03:54:47.197141461Z",
        "code" : -1
      }
    },
    "-229167334" : {
      "success" : {
        "timestamp" : "2025-08-18T03:35:43.926338042Z"
      },
      "error" : {
        "timestamp" : "2025-12-30T03:54:41.344467878Z",
        "code" : -1
      }
    },
    "-1717417194" : {
      "success" : {
        "timestamp" : "2025-12-22T03:46:29.811787827Z"
      }
    },
    "-1039125450" : {
      "success" : {
        "timestamp" : "2025-12-22T03:46:30.045512800Z"
      }
    }
  }
}