{
  "manual" : false,
  "urls" : {
    "1542933168" : {
      "success" : {
        "timestamp" : "2025-04-02T03:46:56.386312107Z"
      },
      "error" : {
        "timestamp" : "2025-04-01T04:33:27.538423205Z",
        "code" : -1
      }
    },
    "1873582383" : {
      "error" : {
        "timestamp" : "2025-10-14T04:19:17.800121825Z",
        "code" : 200
      }
    },
    "593718705" : {
      "error" : {
        "timestamp" : "2025-10-14T04:19:18.740387896Z",
        "code" : 200
      }
    },
    "-686144973" : {
      "error" : {
        "timestamp" : "2025-10-14T04:19:19.657598791Z",
        "code" : 200
      }
    }
  }
}