{
  "manual" : false,
  "urls" : {
    "1507897134" : {
      "success" : {
        "timestamp" : "2025-04-09T04:17:31.683680083Z"
      },
      "error" : {
        "timestamp" : "2025-04-09T04:17:28.785110635Z",
        "code" : -1
      }
    },
    "2128409341" : {
      "error" : {
        "timestamp" : "2025-10-16T04:16:02.487097914Z",
        "code" : 200
      }
    },
    "848545663" : {
      "error" : {
        "timestamp" : "2025-10-16T04:16:03.294797222Z",
        "code" : 200
      }
    },
    "1162498902" : {
      "error" : {
        "timestamp" : "2025-10-16T04:16:04.062629597Z",
        "code" : 200
      }
    }
  }
}