{
  "manual": false,
  "urls": {
    "-1794989742": {
      "success": {
        "timestamp": "2025-12-31T03:40:17.094369636Z"
      },
      "error": {
        "timestamp": "2026-01-16T03:40:26.544194906Z",
        "code": 503
      }
    },
    "191428323": {
      "success": {
        "timestamp": "2025-12-31T03:40:17.620339460Z"
      },
      "error": {
        "timestamp": "2025-12-30T04:24:45.359564061Z",
        "code": -1
      }
    },
    "1354966342": {
      "success": {
        "timestamp": "2026-01-16T03:40:25.058530831Z"
      },
      "error": {
        "timestamp": "2026-01-15T03:40:42.481332088Z",
        "code": 503
      }
    },
    "-1133887562": {
      "success": {
        "timestamp": "2025-12-22T03:46:47.576534455Z"
      }
    },
    "-618529793": {
      "success": {
        "timestamp": "2025-12-22T03:46:47.804898955Z"
      }
    },
    "-2044520350": {
      "success": {
        "timestamp": "2025-12-22T03:46:48.029505232Z"
      }
    }
  }
}