{
  "manual" : false,
  "urls" : {
    "2086519834" : {
      "success" : {
        "timestamp" : "2023-07-07T03:46:56.034578Z"
      }
    },
    "2117812486" : {
      "success" : {
        "timestamp" : "2023-07-07T03:46:56.316391Z"
      }
    },
    "-974487683" : {
      "error" : {
        "timestamp" : "2025-09-09T12:39:25.223847696Z",
        "code" : 200
      }
    },
    "2040615935" : {
      "error" : {
        "timestamp" : "2025-09-09T12:39:25.859598316Z",
        "code" : 200
      }
    },
    "-1940398122" : {
      "error" : {
        "timestamp" : "2025-09-09T12:39:26.439516377Z",
        "code" : 200
      }
    },
    "431618823" : {
      "error" : {
        "timestamp" : "2025-09-09T12:39:26.747923513Z",
        "code" : 200
      }
    }
  }
}