{
  "manual": false,
  "urls": {
    "-2116832512": {
      "success": {
        "timestamp": "2024-12-05T03:59:08.272157261Z"
      }
    },
    "-1639293476": {
      "success": {
        "timestamp": "2024-12-05T03:59:08.750755187Z"
      }
    },
    "198082113": {
      "success": {
        "timestamp": "2024-12-05T03:59:09.908879045Z"
      }
    },
    "-58404459": {
      "error": {
        "timestamp": "2026-04-29T05:07:26.636746690Z",
        "code": 200
      }
    },
    "1742748455": {
      "error": {
        "timestamp": "2026-04-29T05:07:27.642497618Z",
        "code": 200
      }
    },
    "462884777": {
      "error": {
        "timestamp": "2026-04-29T05:07:28.390200590Z",
        "code": 200
      }
    },
    "-816978901": {
      "error": {
        "timestamp": "2026-04-29T05:07:28.871039520Z",
        "code": 200
      }
    },
    "-1358204778": {
      "error": {
        "timestamp": "2026-04-29T05:07:29.238816630Z",
        "code": 200
      }
    }
  }
}