{
  "manual" : false,
  "urls" : {
    "1842200349" : {
      "success" : {
        "timestamp" : "2025-10-12T03:26:53.142727131Z"
      },
      "error" : {
        "timestamp" : "2025-10-11T03:20:30.856414110Z",
        "code" : -1
      }
    },
    "680088731" : {
      "success" : {
        "timestamp" : "2025-08-18T03:40:06.664275916Z"
      },
      "error" : {
        "timestamp" : "2025-08-17T05:32:24.764887524Z",
        "code" : -1
      }
    },
    "-231562417" : {
      "success" : {
        "timestamp" : "2025-08-18T03:40:06.520385450Z"
      },
      "error" : {
        "timestamp" : "2025-10-22T03:29:23.872837615Z",
        "code" : 503
      }
    }
  }
}