{
  "manual": false,
  "urls": {
    "485568183": {
      "success": {
        "timestamp": "2025-10-16T04:12:11.708585106Z"
      }
    },
    "1040254791": {
      "success": {
        "timestamp": "2025-10-16T04:12:12.432078530Z"
      }
    },
    "985976632": {
      "success": {
        "timestamp": "2025-10-16T04:12:13.350741630Z"
      }
    },
    "-2116796965": {
      "success": {
        "timestamp": "2026-07-22T07:34:40.275986749Z"
      }
    },
    "-2129572573": {
      "success": {
        "timestamp": "2026-07-22T07:34:41.304984424Z"
      }
    },
    "1952667228": {
      "success": {
        "timestamp": "2026-07-22T07:34:44.609970487Z"
      }
    }
  }
}