{
  "manual": false,
  "urls": {
    "1838179122": {
      "success": {
        "timestamp": "2025-04-02T03:47:02.574357819Z"
      },
      "error": {
        "timestamp": "2025-04-01T04:38:10.885883002Z",
        "code": -1
      }
    },
    "1589085051": {
      "error": {
        "timestamp": "2026-02-11T05:20:59.250306852Z",
        "code": 200
      }
    },
    "309221373": {
      "error": {
        "timestamp": "2026-02-11T05:21:00.475883851Z",
        "code": 200
      }
    },
    "-970642305": {
      "error": {
        "timestamp": "2026-02-11T05:21:00.995768637Z",
        "code": 200
      }
    }
  }
}