{
  "manual" : false,
  "urls" : {
    "-1792198032" : {
      "success" : {
        "timestamp" : "2025-12-31T03:38:04.836233839Z"
      },
      "error" : {
        "timestamp" : "2025-12-30T04:03:47.828316940Z",
        "code" : -1
      }
    },
    "-65694044" : {
      "success" : {
        "timestamp" : "2025-12-31T03:38:04.135726980Z"
      },
      "error" : {
        "timestamp" : "2025-12-30T04:03:40.509705403Z",
        "code" : -1
      }
    },
    "-896717428" : {
      "success" : {
        "timestamp" : "2025-12-22T03:49:25.803672254Z"
      }
    },
    "-875652160" : {
      "success" : {
        "timestamp" : "2025-12-22T03:49:26.037542406Z"
      }
    }
  }
}