{
  "manual": false,
  "urls": {
    "-431539575": {
      "success": {
        "timestamp": "2023-08-29T12:50:06.168000046Z"
      }
    },
    "-1229423567": {
      "error": {
        "timestamp": "2026-04-21T04:57:05.714978052Z",
        "code": 200
      }
    },
    "1785680051": {
      "error": {
        "timestamp": "2026-04-21T04:57:06.049071130Z",
        "code": 200
      }
    },
    "505816373": {
      "error": {
        "timestamp": "2026-04-21T04:57:06.378802671Z",
        "code": 200
      }
    }
  }
}