{
  "manual": false,
  "urls": {
    "-2042219566": {
      "success": {
        "timestamp": "2026-07-12T06:08:17.797421443Z"
      },
      "error": {
        "timestamp": "2026-07-11T05:45:22.202914717Z",
        "code": 503
      }
    },
    "1261306566": {
      "success": {
        "timestamp": "2026-02-22T03:54:03.369779973Z"
      },
      "error": {
        "timestamp": "2026-02-21T03:50:51.730845760Z",
        "code": 503
      }
    },
    "-1188150278": {
      "success": {
        "timestamp": "2026-06-20T04:34:23.152766057Z"
      },
      "error": {
        "timestamp": "2026-06-19T04:38:57.064838988Z",
        "code": 503
      }
    },
    "1272078830": {
      "success": {
        "timestamp": "2025-12-22T03:48:56.440738783Z"
      }
    },
    "-1043565782": {
      "success": {
        "timestamp": "2025-12-22T03:48:56.667678484Z"
      }
    },
    "-527048098": {
      "success": {
        "timestamp": "2025-12-22T03:48:57.364812930Z"
      }
    }
  }
}