{
  "manual": false,
  "urls": {
    "1630581291": {
      "success": {
        "timestamp": "2026-05-28T05:21:23.865702984Z"
      },
      "error": {
        "timestamp": "2026-05-27T05:28:31.809281726Z",
        "code": -1
      }
    },
    "-2066741830": {
      "success": {
        "timestamp": "2026-05-07T05:12:19.862100555Z"
      },
      "error": {
        "timestamp": "2026-05-06T05:09:08.010388645Z",
        "code": -1
      }
    },
    "-91922925": {
      "success": {
        "timestamp": "2026-06-20T05:22:23.204184948Z"
      },
      "error": {
        "timestamp": "2026-06-19T05:33:06.201682624Z",
        "code": -1
      }
    },
    "-192867877": {
      "success": {
        "timestamp": "2026-06-20T05:22:16.633117502Z"
      },
      "error": {
        "timestamp": "2026-06-19T05:32:57.751035380Z",
        "code": -1
      }
    },
    "1689294260": {
      "success": {
        "timestamp": "2026-06-11T05:25:37.315603463Z"
      },
      "error": {
        "timestamp": "2026-06-09T05:20:58.544036649Z",
        "code": -1
      }
    }
  }
}