{
  "manual": false,
  "urls": {
    "-144163532": {
      "success": {
        "timestamp": "2023-07-07T03:46:28.356995Z"
      }
    },
    "-1349058228": {
      "error": {
        "timestamp": "2026-04-15T05:28:28.361933548Z",
        "code": 200
      }
    },
    "1666045390": {
      "error": {
        "timestamp": "2026-04-15T05:28:29.856346809Z",
        "code": 200
      }
    },
    "386181712": {
      "error": {
        "timestamp": "2026-04-15T05:28:30.556604873Z",
        "code": 200
      }
    }
  }
}