{
  "manual" : false,
  "urls" : {
    "1439269498" : {
      "success" : {
        "timestamp" : "2025-12-25T04:29:36.833893810Z"
      },
      "error" : {
        "timestamp" : "2025-12-24T04:57:11.392729855Z",
        "code" : -1
      }
    },
    "-900684195" : {
      "success" : {
        "timestamp" : "2024-10-11T17:31:41.187901206Z"
      }
    },
    "-148434977" : {
      "success" : {
        "timestamp" : "2024-10-11T17:31:41.364239263Z"
      }
    },
    "-688534329" : {
      "success" : {
        "timestamp" : "2023-07-26T03:58:59.707516Z"
      }
    }
  }
}