{
  "manual": false,
  "urls": {
    "1053404300": {
      "success": {
        "timestamp": "2025-12-31T03:47:37.070367436Z"
      },
      "error": {
        "timestamp": "2025-12-30T05:41:35.203424024Z",
        "code": -1
      }
    },
    "-547971991": {
      "success": {
        "timestamp": "2025-12-31T03:47:37.372674944Z"
      },
      "error": {
        "timestamp": "2026-01-17T03:43:00.191456880Z",
        "code": 503
      }
    },
    "1773960652": {
      "success": {
        "timestamp": "2026-01-08T03:47:19.129754566Z"
      },
      "error": {
        "timestamp": "2026-01-07T03:43:32.914908135Z",
        "code": 503
      }
    },
    "-1503933440": {
      "success": {
        "timestamp": "2026-01-17T03:42:59.095354147Z"
      },
      "error": {
        "timestamp": "2026-01-16T03:48:01.694069103Z",
        "code": 503
      }
    }
  }
}