{
  "manual" : false,
  "urls" : {
    "1861118255" : {
      "success" : {
        "timestamp" : "2023-10-04T03:39:24.650442852Z"
      }
    },
    "-1245625011" : {
      "success" : {
        "timestamp" : "2023-10-04T03:39:25.428507940Z"
      }
    },
    "939344816" : {
      "success" : {
        "timestamp" : "2023-10-04T03:39:25.872915516Z"
      }
    },
    "162787362" : {
      "error" : {
        "timestamp" : "2025-12-17T04:28:45.269102497Z",
        "code" : 200
      }
    },
    "-1506511494" : {
      "error" : {
        "timestamp" : "2025-12-17T04:28:45.684043333Z",
        "code" : 200
      }
    },
    "1508592124" : {
      "error" : {
        "timestamp" : "2025-12-17T04:28:46.080677341Z",
        "code" : 200
      }
    },
    "228728446" : {
      "error" : {
        "timestamp" : "2025-12-17T04:28:46.454956262Z",
        "code" : 200
      }
    },
    "459521251" : {
      "error" : {
        "timestamp" : "2025-12-17T04:28:46.725052571Z",
        "code" : 200
      }
    }
  }
}