{
  "manual": false,
  "urls": {
    "-137815304": {
      "success": {
        "timestamp": "2024-02-09T03:43:46.810616479Z"
      }
    },
    "-1753722140": {
      "success": {
        "timestamp": "2024-02-09T03:43:47.495083484Z"
      }
    },
    "-535871431": {
      "success": {
        "timestamp": "2024-02-09T03:43:47.774902535Z"
      }
    },
    "602846517": {
      "error": {
        "timestamp": "2026-06-07T05:56:37.655178393Z",
        "code": 200
      }
    },
    "55587719": {
      "error": {
        "timestamp": "2026-06-07T05:56:41.937249998Z",
        "code": 200
      }
    },
    "-1224275959": {
      "error": {
        "timestamp": "2026-06-07T05:56:44.138236423Z",
        "code": 200
      }
    },
    "1790827659": {
      "error": {
        "timestamp": "2026-06-07T05:56:45.317065970Z",
        "code": 200
      }
    },
    "-1777300426": {
      "error": {
        "timestamp": "2026-06-07T05:56:45.898716289Z",
        "code": 200
      }
    }
  }
}