{
  "manual": false,
  "urls": {
    "1289876726": {
      "success": {
        "timestamp": "2025-02-24T04:08:38.185750951Z"
      },
      "error": {
        "timestamp": "2025-02-24T04:08:35.158372715Z",
        "code": -1
      }
    },
    "1528271350": {
      "error": {
        "timestamp": "2026-07-15T07:10:32.895763406Z",
        "code": 200
      }
    },
    "1842224589": {
      "error": {
        "timestamp": "2026-07-15T07:10:33.221393691Z",
        "code": 200
      }
    },
    "562360911": {
      "error": {
        "timestamp": "2026-07-15T07:10:33.611235425Z",
        "code": 200
      }
    }
  }
}