{
  "manual": false,
  "urls": {
    "1289876726": {
      "success": {
        "timestamp": "2025-02-24T04:08:38.185750951Z"
      },
      "error": {
        "timestamp": "2025-02-24T04:08:35.158372715Z",
        "code": -1
      }
    },
    "1528271350": {
      "error": {
        "timestamp": "2026-06-08T05:58:17.467609920Z",
        "code": 200
      }
    },
    "1842224589": {
      "error": {
        "timestamp": "2026-06-08T05:58:18.692572664Z",
        "code": 200
      }
    },
    "562360911": {
      "error": {
        "timestamp": "2026-06-08T05:58:19.399451889Z",
        "code": 200
      }
    }
  }
}