{
  "manual" : false,
  "urls" : {
    "1998318281" : {
      "error" : {
        "timestamp" : "2023-04-28T14:10:08.107770700Z",
        "code" : 404
      }
    },
    "1895100771" : {
      "success" : {
        "timestamp" : "2023-04-28T14:10:08.565694800Z"
      }
    },
    "-268342977" : {
      "error" : {
        "timestamp" : "2023-04-28T14:10:09.114071300Z",
        "code" : 404
      }
    },
    "55800132" : {
      "success" : {
        "timestamp" : "2023-04-28T14:10:09.569397600Z"
      }
    },
    "-2107643616" : {
      "error" : {
        "timestamp" : "2023-04-28T14:10:10.205691800Z",
        "code" : 404
      }
    }
  }
}