{
  "manual" : false,
  "urls" : {
    "-879370707" : {
      "success" : {
        "timestamp" : "2023-04-28T14:09:29.364495600Z"
      }
    },
    "-1413911937" : {
      "success" : {
        "timestamp" : "2023-04-28T14:09:30.765605600Z"
      }
    },
    "717611611" : {
      "success" : {
        "timestamp" : "2023-04-28T14:09:32.246966600Z"
      }
    },
    "1041754720" : {
      "success" : {
        "timestamp" : "2023-04-28T14:09:33.575103900Z"
      }
    },
    "-1121689028" : {
      "success" : {
        "timestamp" : "2023-04-28T14:09:34.865496700Z"
      }
    }
  }
}