{
  "manual" : false,
  "urls" : {
    "-195570423" : {
      "success" : {
        "timestamp" : "2023-04-28T14:11:40.137462300Z"
      }
    },
    "-1690939613" : {
      "success" : {
        "timestamp" : "2023-04-28T14:11:41.306252200Z"
      }
    },
    "440583935" : {
      "success" : {
        "timestamp" : "2023-04-28T14:11:42.266865200Z"
      }
    },
    "764727044" : {
      "success" : {
        "timestamp" : "2023-04-28T14:11:43.144348400Z"
      }
    },
    "-1398716704" : {
      "error" : {
        "timestamp" : "2023-04-28T14:11:43.823825200Z",
        "code" : 404
      }
    }
  }
}