{
  "manual" : false,
  "urls" : {
    "-955302580" : {
      "success" : {
        "timestamp" : "2024-02-09T03:43:48.094429994Z"
      }
    },
    "1242374160" : {
      "success" : {
        "timestamp" : "2024-02-09T03:43:48.760640707Z"
      }
    },
    "-1646087795" : {
      "success" : {
        "timestamp" : "2024-02-09T03:43:49.042495766Z"
      }
    },
    "-1046535489" : {
      "error" : {
        "timestamp" : "2025-12-14T04:29:53.178531574Z",
        "code" : 200
      }
    },
    "2037080509" : {
      "error" : {
        "timestamp" : "2025-12-14T04:29:54.040923621Z",
        "code" : 200
      }
    },
    "757216831" : {
      "error" : {
        "timestamp" : "2025-12-14T04:29:54.693338088Z",
        "code" : 200
      }
    },
    "-522646847" : {
      "error" : {
        "timestamp" : "2025-12-14T04:29:55.090620555Z",
        "code" : 200
      }
    },
    "-1512281792" : {
      "error" : {
        "timestamp" : "2025-12-14T04:29:55.427867111Z",
        "code" : 200
      }
    }
  }
}