{
  "manual" : false,
  "urls" : {
    "1803143088" : {
      "success" : {
        "timestamp" : "2025-04-02T03:46:44.829455880Z"
      },
      "error" : {
        "timestamp" : "2025-04-01T04:27:52.017963865Z",
        "code" : -1
      }
    },
    "1964694879" : {
      "error" : {
        "timestamp" : "2025-09-13T04:09:31.735372111Z",
        "code" : 200
      }
    },
    "684831201" : {
      "error" : {
        "timestamp" : "2025-09-13T04:09:32.569454432Z",
        "code" : 200
      }
    },
    "998784440" : {
      "error" : {
        "timestamp" : "2025-09-13T04:09:33.311442664Z",
        "code" : 200
      }
    }
  }
}