{
  "manual" : false,
  "urls" : {
    "2036961530" : {
      "success" : {
        "timestamp" : "2023-07-07T03:46:18.492004Z"
      }
    },
    "2079022566" : {
      "success" : {
        "timestamp" : "2023-07-07T03:46:18.719404Z"
      }
    },
    "1317079776" : {
      "error" : {
        "timestamp" : "2025-09-13T04:07:11.348676884Z",
        "code" : 200
      }
    },
    "1631033015" : {
      "error" : {
        "timestamp" : "2025-09-13T04:07:12.085710856Z",
        "code" : 200
      }
    },
    "774099718" : {
      "error" : {
        "timestamp" : "2025-09-13T04:07:12.958723523Z",
        "code" : 200
      }
    }
  }
}