{
  "manual": false,
  "urls": {
    "2036961530": {
      "success": {
        "timestamp": "2023-07-07T03:46:18.492004Z"
      }
    },
    "2079022566": {
      "success": {
        "timestamp": "2023-07-07T03:46:18.719404Z"
      }
    },
    "1317079776": {
      "error": {
        "timestamp": "2026-01-22T04:52:47.453811545Z",
        "code": 200
      }
    },
    "1631033015": {
      "error": {
        "timestamp": "2026-01-22T04:52:49.656541506Z",
        "code": 200
      }
    },
    "774099718": {
      "error": {
        "timestamp": "2026-01-22T04:52:50.304097995Z",
        "code": 200
      }
    }
  }
}