{
  "manual": false,
  "urls": {
    "-1440974832": {
      "success": {
        "timestamp": "2024-03-22T03:49:58.790128554Z"
      }
    },
    "593081116": {
      "error": {
        "timestamp": "2026-01-19T04:35:31.633227717Z",
        "code": 200
      }
    },
    "-686782562": {
      "error": {
        "timestamp": "2026-01-19T04:35:32.226217285Z",
        "code": 200
      }
    },
    "-1966646240": {
      "error": {
        "timestamp": "2026-01-19T04:35:32.553997605Z",
        "code": 200
      }
    }
  }
}