{
  "manual" : false,
  "urls" : {
    "-1440974832" : {
      "success" : {
        "timestamp" : "2024-03-22T03:49:58.790128554Z"
      }
    },
    "593081116" : {
      "error" : {
        "timestamp" : "2025-09-10T04:34:09.394489468Z",
        "code" : 200
      }
    },
    "-686782562" : {
      "error" : {
        "timestamp" : "2025-09-10T04:34:10.963711465Z",
        "code" : 200
      }
    },
    "-1966646240" : {
      "error" : {
        "timestamp" : "2025-09-10T04:34:11.454100930Z",
        "code" : 200
      }
    }
  }
}