{
  "manual" : false,
  "urls" : {
    "1843869906" : {
      "success" : {
        "timestamp" : "2025-08-18T03:39:39.324671861Z"
      },
      "error" : {
        "timestamp" : "2025-08-17T05:20:57.338605764Z",
        "code" : -1
      }
    },
    "-1076662429" : {
      "success" : {
        "timestamp" : "2025-08-18T03:39:39.469484431Z"
      },
      "error" : {
        "timestamp" : "2025-08-17T05:21:02.356050944Z",
        "code" : -1
      }
    },
    "708697542" : {
      "success" : {
        "timestamp" : "2025-11-21T03:33:01.089105900Z"
      },
      "error" : {
        "timestamp" : "2025-11-20T03:34:24.910621070Z",
        "code" : 503
      }
    },
    "-2032623878" : {
      "success" : {
        "timestamp" : "2025-10-06T03:26:40.295505592Z"
      },
      "error" : {
        "timestamp" : "2025-11-30T03:40:56.274438822Z",
        "code" : 503
      }
    }
  }
}