{
  "manual": false,
  "urls": {
    "-1752990917": {
      "success": {
        "timestamp": "2026-01-15T03:41:29.151113702Z"
      },
      "error": {
        "timestamp": "2026-01-14T03:44:59.078521595Z",
        "code": 503
      }
    },
    "1843002813": {
      "success": {
        "timestamp": "2025-12-31T03:40:59.389339309Z"
      },
      "error": {
        "timestamp": "2025-12-30T04:32:18.562451477Z",
        "code": -1
      }
    },
    "1592126321": {
      "success": {
        "timestamp": "2025-12-31T03:40:58.701366977Z"
      },
      "error": {
        "timestamp": "2025-12-30T04:32:13.217597396Z",
        "code": -1
      }
    },
    "1561307479": {
      "success": {
        "timestamp": "2025-12-22T03:47:54.889929007Z"
      }
    },
    "-461869535": {
      "success": {
        "timestamp": "2025-12-22T03:47:56.149529200Z"
      }
    },
    "-2041738795": {
      "success": {
        "timestamp": "2025-12-22T03:47:57.269476648Z"
      }
    }
  }
}