{
  "manual": false,
  "urls": {
    "708842695": {
      "success": {
        "timestamp": "2025-01-11T03:26:07.202364981Z"
      },
      "error": {
        "timestamp": "2026-04-05T04:27:01.718023563Z",
        "code": 502
      }
    },
    "-739892736": {
      "success": {
        "timestamp": "2024-10-11T14:52:30.352004250Z"
      },
      "error": {
        "timestamp": "2026-04-05T04:27:01.764450235Z",
        "code": 502
      }
    },
    "-1460601384": {
      "success": {
        "timestamp": "2025-01-10T03:29:55.786561099Z"
      },
      "error": {
        "timestamp": "2026-04-05T04:27:01.671619806Z",
        "code": 502
      }
    },
    "1179238450": {
      "success": {
        "timestamp": "2025-01-10T03:29:55.914431435Z"
      },
      "error": {
        "timestamp": "2026-04-05T04:27:01.810889150Z",
        "code": 502
      }
    },
    "-2097076762": {
      "success": {
        "timestamp": "2024-10-11T14:52:48.411620529Z"
      },
      "error": {
        "timestamp": "2026-04-05T04:27:01.857290785Z",
        "code": 502
      }
    }
  }
}