{
  "manual" : false,
  "urls" : {
    "104220003" : {
      "success" : {
        "timestamp" : "2025-08-30T03:19:29.820352265Z"
      },
      "error" : {
        "timestamp" : "2025-08-29T03:27:19.118478694Z",
        "code" : -1
      }
    },
    "1196128917" : {
      "success" : {
        "timestamp" : "2025-12-19T03:39:17.259546977Z"
      },
      "error" : {
        "timestamp" : "2025-12-18T03:37:17.844818901Z",
        "code" : 503
      }
    },
    "-149078967" : {
      "success" : {
        "timestamp" : "2025-11-22T03:28:12.522705002Z"
      },
      "error" : {
        "timestamp" : "2025-11-21T03:32:07.152383912Z",
        "code" : 503
      }
    },
    "765322183" : {
      "success" : {
        "timestamp" : "2025-12-22T03:48:24.549430408Z"
      }
    },
    "2091609521" : {
      "success" : {
        "timestamp" : "2025-12-22T03:48:24.873100945Z"
      }
    },
    "-959037083" : {
      "success" : {
        "timestamp" : "2025-12-22T03:48:25.545617765Z"
      }
    }
  }
}