{
  "manual": false,
  "urls": {
    "1057517162": {
      "success": {
        "timestamp": "2026-01-17T03:43:29.858111476Z"
      },
      "error": {
        "timestamp": "2026-01-20T03:48:08.461971972Z",
        "code": 503
      }
    },
    "484588958": {
      "success": {
        "timestamp": "2026-01-16T03:48:54.920145196Z"
      },
      "error": {
        "timestamp": "2026-01-15T03:48:14.422649198Z",
        "code": 503
      }
    },
    "1952997766": {
      "success": {
        "timestamp": "2025-12-22T03:50:16.313462023Z"
      }
    },
    "-325369158": {
      "success": {
        "timestamp": "2025-12-22T03:50:16.547872360Z"
      }
    }
  }
}