{
  "manual": false,
  "urls": {
    "-741158785": {
      "success": {
        "timestamp": "2026-04-08T05:10:34.184489587Z"
      }
    },
    "1493872767": {
      "success": {
        "timestamp": "2026-04-08T05:10:35.126862418Z"
      }
    },
    "-1663736064": {
      "success": {
        "timestamp": "2026-04-08T05:10:36.151910138Z"
      }
    },
    "-1780916232": {
      "error": {
        "timestamp": "2026-06-22T06:02:30.527155955Z",
        "code": 200
      }
    },
    "1383907942": {
      "error": {
        "timestamp": "2026-06-22T06:02:31.374943255Z",
        "code": 200
      }
    },
    "104044264": {
      "error": {
        "timestamp": "2026-06-22T06:02:31.860222244Z",
        "code": 200
      }
    },
    "-1175819414": {
      "error": {
        "timestamp": "2026-06-22T06:02:33.599830318Z",
        "code": 200
      }
    },
    "1291273529": {
      "error": {
        "timestamp": "2026-06-22T06:02:33.915059179Z",
        "code": 200
      }
    }
  }
}