{
  "manual" : false,
  "urls" : {
    "-1363007155" : {
      "success" : {
        "timestamp" : "2023-12-09T03:41:07.436993485Z"
      }
    },
    "1482893423" : {
      "success" : {
        "timestamp" : "2023-12-09T03:41:07.923153368Z"
      }
    },
    "-785190322" : {
      "success" : {
        "timestamp" : "2023-12-09T03:41:08.201156597Z"
      }
    },
    "239388634" : {
      "error" : {
        "timestamp" : "2025-11-11T04:18:56.371606094Z",
        "code" : 200
      }
    },
    "-105651518" : {
      "error" : {
        "timestamp" : "2025-11-11T04:18:57.301768713Z",
        "code" : 200
      }
    },
    "-1385515196" : {
      "error" : {
        "timestamp" : "2025-11-11T04:18:58.328327575Z",
        "code" : 200
      }
    },
    "1629588422" : {
      "error" : {
        "timestamp" : "2025-11-11T04:18:58.771136134Z",
        "code" : 200
      }
    },
    "-1266762085" : {
      "error" : {
        "timestamp" : "2025-11-11T04:18:59.108973244Z",
        "code" : 200
      }
    }
  }
}