{
  "manual": false,
  "urls": {
    "-1165822822": {
      "success": {
        "timestamp": "2025-01-17T03:46:21.049367042Z"
      },
      "error": {
        "timestamp": "2025-01-16T03:38:38.007653693Z",
        "code": 403
      }
    },
    "1828815671": {
      "error": {
        "timestamp": "2026-05-18T05:57:28.365998118Z",
        "code": 200
      }
    },
    "548951993": {
      "error": {
        "timestamp": "2026-05-18T05:57:28.844258788Z",
        "code": 200
      }
    },
    "-730911685": {
      "error": {
        "timestamp": "2026-05-18T05:57:29.303163747Z",
        "code": 200
      }
    }
  }
}