{
  "manual" : false,
  "urls" : {
    "-1165822822" : {
      "success" : {
        "timestamp" : "2025-01-17T03:46:21.049367042Z"
      },
      "error" : {
        "timestamp" : "2025-01-16T03:38:38.007653693Z",
        "code" : 403
      }
    },
    "1828815671" : {
      "error" : {
        "timestamp" : "2025-10-31T04:29:41.562340961Z",
        "code" : 200
      }
    },
    "548951993" : {
      "error" : {
        "timestamp" : "2025-10-31T04:29:42.735150212Z",
        "code" : 200
      }
    },
    "-730911685" : {
      "error" : {
        "timestamp" : "2025-10-31T04:29:43.214439967Z",
        "code" : 200
      }
    }
  }
}