{
  "manual": false,
  "urls": {
    "-134855103": {
      "success": {
        "timestamp": "2026-06-03T05:12:16.607895940Z"
      }
    },
    "-613139483": {
      "success": {
        "timestamp": "2026-06-03T05:12:23.787020515Z"
      }
    },
    "-1971738261": {
      "success": {
        "timestamp": "2026-06-03T05:12:24.044273478Z"
      }
    },
    "159785287": {
      "success": {
        "timestamp": "2026-06-03T05:12:24.974004705Z"
      }
    },
    "-522492132": {
      "success": {
        "timestamp": "2026-06-03T05:12:25.880955662Z"
      }
    },
    "1609031416": {
      "success": {
        "timestamp": "2026-06-03T05:12:26.771080677Z"
      }
    }
  }
}