{
  "manual" : false,
  "urls" : {
    "264441125" : {
      "success" : {
        "timestamp" : "2023-04-28T14:12:08.165494500Z"
      }
    },
    "-315483513" : {
      "success" : {
        "timestamp" : "2023-04-28T14:12:09.273555300Z"
      }
    },
    "1816040035" : {
      "success" : {
        "timestamp" : "2023-04-28T14:12:10.296832600Z"
      }
    },
    "2140183144" : {
      "success" : {
        "timestamp" : "2023-04-28T14:12:11.494086100Z"
      }
    },
    "-23260604" : {
      "error" : {
        "timestamp" : "2023-04-28T14:12:12.254614500Z",
        "code" : 404
      }
    }
  }
}