{
  "manual" : false,
  "urls" : {
    "795544512" : {
      "success" : {
        "timestamp" : "2023-12-06T03:45:28.154435986Z"
      }
    },
    "-1649717988" : {
      "success" : {
        "timestamp" : "2023-12-06T03:45:28.591560188Z"
      }
    },
    "822568705" : {
      "success" : {
        "timestamp" : "2023-12-06T03:45:28.868850618Z"
      }
    },
    "-1593289348" : {
      "error" : {
        "timestamp" : "2025-12-22T04:41:51.614549710Z",
        "code" : 200
      }
    },
    "208853472" : {
      "error" : {
        "timestamp" : "2025-12-22T04:41:52.170061947Z",
        "code" : 200
      }
    },
    "-1071010206" : {
      "error" : {
        "timestamp" : "2025-12-22T04:41:52.709675916Z",
        "code" : 200
      }
    },
    "1944093412" : {
      "error" : {
        "timestamp" : "2025-12-22T04:41:53.184730209Z",
        "code" : 200
      }
    },
    "1306373565" : {
      "error" : {
        "timestamp" : "2025-12-22T04:41:53.522725258Z",
        "code" : 200
      }
    }
  }
}